tox_py_backwards.py
tox_py_backwards-0.1.dist-info/DESCRIPTION.rst
tox_py_backwards-0.1.dist-info/METADATA
tox_py_backwards-0.1.dist-info/RECORD
tox_py_backwards-0.1.dist-info/WHEEL
tox_py_backwards-0.1.dist-info/entry_points.txt
tox_py_backwards-0.1.dist-info/metadata.json
tox_py_backwards-0.1.dist-info/top_level.txt
