Metadata-Version: 2.0
Name: tox-py-backwards
Version: 0.1
Summary: tox plugin for py-backwards
Home-page: https://github.com/nvbn/tox-py-backwards
Author: Vladimir Iakovlev
Author-email: nvbn.rm@gmail.com
License: MIT 
Platform: UNKNOWN
Requires-Dist: tox (>=2.0)
